pyproject.toml
albert/__init__.py
albert/albert.py
albert/api/__init__.py
albert/api/api_client.py
albert/api/apis/__init__.py
albert/api/apis/path_to_api.py
albert/api/apis/paths/__init__.py
albert/api/apis/paths/api_v3_inventories.py
albert/api/apis/paths/api_v3_inventories_health.py
albert/api/apis/paths/api_v3_inventories_id.py
albert/api/apis/paths/api_v3_locations.py
albert/api/apis/paths/api_v3_locations_async_id.py
albert/api/apis/paths/api_v3_locations_health.py
albert/api/apis/paths/api_v3_locations_id.py
albert/api/apis/paths/api_v3_predictions.py
albert/api/apis/paths/api_v3_predictions_health.py
albert/api/apis/paths/api_v3_predictions_mergedac.py
albert/api/apis/paths/api_v3_predictions_mergedat.py
albert/api/apis/paths/api_v3_predictions_models.py
albert/api/apis/paths/api_v3_predictions_models_id.py
albert/api/apis/paths/api_v3_predictions_models_parent_id_version.py
albert/api/apis/paths/api_v3_predictions_models_parent_id_version_id.py
albert/api/apis/paths/api_v3_predictions_parent_id.py
albert/api/apis/paths/api_v3_predictions_tasks.py
albert/api/apis/paths/api_v3_productdesign.py
albert/api/apis/paths/api_v3_productdesign_health.py
albert/api/apis/paths/api_v3_productdesign_id.py
albert/api/apis/paths/api_v3_productdesign_id_designs.py
albert/api/apis/paths/api_v3_productdesign_id_grid.py
albert/api/apis/paths/api_v3_productdesign_id_products.py
albert/api/apis/paths/api_v3_productdesign_id_unpack.py
albert/api/apis/paths/api_v3_productdesign_id_values.py
albert/api/apis/paths/api_v3_productdesign_inventories_id.py
albert/api/apis/paths/api_v3_productdesign_mergeinventory.py
albert/api/apis/paths/api_v3_productdesign_search.py
albert/api/apis/paths/api_v3_productdesign_suggest.py
albert/api/apis/paths/api_v3_reports.py
albert/api/apis/paths/api_v3_reports_analytics_id.py
albert/api/apis/paths/api_v3_reports_copy.py
albert/api/apis/paths/api_v3_reports_datascience_id.py
albert/api/apis/paths/api_v3_reports_health.py
albert_toolkit-0.1.1.dist-info/METADATA
albert_toolkit-0.1.1.dist-info/WHEEL
albert_toolkit-0.1.1.dist-info/entry_points.txt
albert_toolkit-0.1.1.dist-info/RECORD
