Metadata-Version: 2.1
Name: albert-toolkit
Version: 0.1.1
Summary: Python toolkit for Albert Invent
License: MIT
Author: Jonathan Welch
Author-email: Jonathan@albertinvent.com
Requires-Python: >=3.10,<3.12
Classifier: License :: OSI Approved :: MIT License
Classifier: Programming Language :: Python :: 3
Classifier: Programming Language :: Python :: 3.10
Classifier: Programming Language :: Python :: 3.11
Provides-Extra: chem
Provides-Extra: dev
Provides-Extra: viz
Requires-Dist: aiohttp (==3.8.3)
Requires-Dist: boto3 (>=1.26.56,<1.27.0) ; extra == "dev"
Requires-Dist: botocore (>=1.29.56,<1.30.0) ; extra == "dev"
Requires-Dist: build (>=0.10.0) ; extra == "dev"
Requires-Dist: certifi (>=14.5.14)
Requires-Dist: click (>=8.1.3,<9.0.0)
Requires-Dist: deepdiff (>=6.2.3)
Requires-Dist: distance (>=0.1.3)
Requires-Dist: frozendict (==2.3.4)
Requires-Dist: gpytorch (==1.9.1) ; extra == "dev"
Requires-Dist: hdbscan (==0.8.29) ; extra == "viz" or extra == "dev"
Requires-Dist: jupyterlab (==3.5.2) ; extra == "dev"
Requires-Dist: lightning (>=2.0.0,<3.0.0) ; extra == "dev"
Requires-Dist: notebook (==6.5.2) ; extra == "dev"
Requires-Dist: openpyxl (==3.1.2)
Requires-Dist: pint (==0.18)
Requires-Dist: plotly (==5.12.0) ; extra == "viz" or extra == "dev"
Requires-Dist: pymysql (>=1.0.2,<2.0.0) ; extra == "dev"
Requires-Dist: pytest (==7.2.1) ; extra == "dev"
Requires-Dist: pytest-cov (==4.0.0) ; extra == "dev"
Requires-Dist: pytest-dotenv (>=0.5.2,<0.6.0) ; extra == "dev"
Requires-Dist: python-dateutil (>=2.7.0,<2.8.0)
Requires-Dist: python-dotenv (>=0.5.2)
Requires-Dist: python-jose (==3.3.0)
Requires-Dist: python-levenshtein (==0.20.9) ; extra == "dev"
Requires-Dist: qcelemental (==0.25.1)
Requires-Dist: rdkit (>=2022.9.5) ; extra == "chem" or extra == "dev"
Requires-Dist: roman (==4.0)
Requires-Dist: scikit-learn (==1.2.2)
Requires-Dist: scipy (==1.10.0) ; extra == "viz" or extra == "dev"
Requires-Dist: seaborn (==0.12.2) ; extra == "viz" or extra == "dev"
Requires-Dist: sqlacodegen (==2.3.0) ; extra == "dev"
Requires-Dist: torch (==1.13.1) ; extra == "dev"
Requires-Dist: transformers (==4.25.1) ; extra == "dev"
Requires-Dist: typing-extensions (>=4.3.0,<4.4.0)
Requires-Dist: umap-learn[plot] (==0.5.3) ; extra == "viz" or extra == "dev"
Requires-Dist: urllib3 (>=1.26.7,<1.27.0)
